[
    {
        "user1":"56782833",
        "password1":"Hunter980525*",
        "anuncio1":"Se vende Pley4 interesados al pv",
        "ruta1":"Program.png",
        "grupo1":[
                "https://www.facebook.com/groups/4557502567593141",
                "https://www.facebook.com/groups/1020966382043081",
		"https://www.facebook.com/groups/584987869945784",
		"https://www.facebook.com/groups/4557502567593141"
            ]
    },
    {
        "id_grupos":["Jjj","Jfjdx","Revolico"],
        "mensaje":"Ejemplo de anuncio:-_-_-_-_-_-_-_-_-_-_-_-_-_-_-_-_-_-_-_-_-_-_-_\n SE Vende LAPTOP HP DE USO \n-Procesador AMD A6-5200 \n-4gb de ram✓500gb de almacenamiento \n✓La batería no le sirve \n30mil cup \n Interesados al pv \n_-_-_-_-_-_-_-_-_-_-_-_-_-_-_-_-_-_-_-_-_-_-_-_-",
        "ruta":"Program.png"

    }
]
